{
    "AX": {
        "error": 0.004615190437197064, 
        "filter_outliers_dict": {
            "filter_outliers": true, 
            "iterations": 1, 
            "std_devs": 2
        }, 
        "fit": "average", 
        "value": -0.056526749740259834
    }, 
    "CDD": {
        "error": 3.497699260314956e-06, 
        "filter_outliers_dict": {
            "filter_outliers": true, 
            "iterations": 1, 
            "std_devs": 10
        }, 
        "fit": "average", 
        "value": 7.531321891910684e-06
    }, 
    "H1": {
        "error": 0.0031570928300247935, 
        "filter_outliers_dict": {
            "filter_outliers": true, 
            "iterations": 1, 
            "std_devs": 2
        }, 
        "fit": "average", 
        "value": 0.1324022643192664
    }, 
    "H2": {
        "error": 0.0053470771636494096, 
        "filter_outliers_dict": {
            "filter_outliers": true, 
            "iterations": 1, 
            "std_devs": 2
        }, 
        "fit": "average", 
        "value": -0.20597886125226655
    }, 
    "L1": {
        "error": 0.0019598999202298907, 
        "filter_outliers_dict": {
            "filter_outliers": true, 
            "iterations": 1, 
            "std_devs": 2
        }, 
        "fit": "average", 
        "value": -0.031913159417579155
    }, 
    "L2": {
        "error": 0.00452992851801627, 
        "filter_outliers_dict": {
            "filter_outliers": true, 
            "iterations": 1, 
            "std_devs": 2
        }, 
        "fit": "average", 
        "value": -0.026447364194905662
    }
}