{
    "AX": {
        "error": 0.004880586762993325, 
        "filter_outliers_dict": {
            "filter_outliers": true, 
            "iterations": 1, 
            "std_devs": 2
        }, 
        "fit": "average", 
        "value": -0.06126097967260646
    }, 
    "CDD": {
        "error": 3.937754769374518e-06, 
        "filter_outliers_dict": {
            "filter_outliers": true, 
            "iterations": 1, 
            "std_devs": 10
        }, 
        "fit": "average", 
        "value": 1.3645996026816726e-05
    }, 
    "H1": {
        "error": 0.010451723040318559, 
        "filter_outliers_dict": {
            "filter_outliers": true, 
            "iterations": 1, 
            "std_devs": 2
        }, 
        "fit": "average", 
        "value": -0.1546349225677039
    }, 
    "H2": {
        "error": 0.005692066817995344, 
        "filter_outliers_dict": {
            "filter_outliers": true, 
            "iterations": 1, 
            "std_devs": 2
        }, 
        "fit": "average", 
        "value": -0.2024476625919789
    }, 
    "L1": {
        "error": 0.002080077017390345, 
        "filter_outliers_dict": {
            "filter_outliers": true, 
            "iterations": 1, 
            "std_devs": 2
        }, 
        "fit": "average", 
        "value": -0.027433065030317217
    }, 
    "L2": {
        "error": 0.004347274922054379, 
        "filter_outliers_dict": {
            "filter_outliers": true, 
            "iterations": 1, 
            "std_devs": 2
        }, 
        "fit": "average", 
        "value": -0.017736882628891008
    }
}