{
    "AX": {
        "error": 0.004122662430898818, 
        "filter_outliers_dict": {
            "filter_outliers": true, 
            "iterations": 1, 
            "std_devs": 2
        }, 
        "fit": "average", 
        "value": -0.053557141598818386
    }, 
    "CDD": {
        "error": 4.2121019862687814e-06, 
        "filter_outliers_dict": {
            "filter_outliers": true, 
            "iterations": 1, 
            "std_devs": 10
        }, 
        "fit": "average", 
        "value": 1.2552203137223518e-05
    }, 
    "H1": {
        "error": 0.0033687570089342, 
        "filter_outliers_dict": {
            "filter_outliers": true, 
            "iterations": 1, 
            "std_devs": 2
        }, 
        "fit": "average", 
        "value": 0.10429996983752206
    }, 
    "H2": {
        "error": 0.005020708992764768, 
        "filter_outliers_dict": {
            "filter_outliers": true, 
            "iterations": 1, 
            "std_devs": 2
        }, 
        "fit": "average", 
        "value": -0.19901677414555527
    }, 
    "L1": {
        "error": 0.001843044479019921, 
        "filter_outliers_dict": {
            "filter_outliers": true, 
            "iterations": 1, 
            "std_devs": 2
        }, 
        "fit": "average", 
        "value": -0.03144350545501909
    }, 
    "L2": {
        "error": 0.0041363003312603844, 
        "filter_outliers_dict": {
            "filter_outliers": true, 
            "iterations": 1, 
            "std_devs": 2
        }, 
        "fit": "average", 
        "value": -0.030619038885439754
    }
}