{
    "AX": {
        "error": 0.0041040277065579195, 
        "filter_outliers_dict": {
            "filter_outliers": true, 
            "iterations": 1, 
            "std_devs": 2
        }, 
        "fit": "average", 
        "value": -0.06837821426372996
    }, 
    "CDD": {
        "error": 6.08762551533263e-06, 
        "filter_outliers_dict": {
            "filter_outliers": true, 
            "iterations": 1, 
            "std_devs": 10
        }, 
        "fit": "average", 
        "value": 2.635962660971668e-05
    }, 
    "H1": {
        "error": 0.0031039614230595554, 
        "filter_outliers_dict": {
            "filter_outliers": true, 
            "iterations": 1, 
            "std_devs": 2
        }, 
        "fit": "average", 
        "value": 0.11481616576897388
    }, 
    "H2": {
        "error": 0.005915016920787794, 
        "filter_outliers_dict": {
            "filter_outliers": true, 
            "iterations": 1, 
            "std_devs": 2
        }, 
        "fit": "average", 
        "value": -0.20525606029854906
    }, 
    "L1": {
        "error": 0.001981988915320838, 
        "filter_outliers_dict": {
            "filter_outliers": true, 
            "iterations": 1, 
            "std_devs": 2
        }, 
        "fit": "average", 
        "value": -0.03490027124010606
    }, 
    "L2": {
        "error": 0.004604654828188196, 
        "filter_outliers_dict": {
            "filter_outliers": true, 
            "iterations": 1, 
            "std_devs": 2
        }, 
        "fit": "average", 
        "value": -0.028399552384653234
    }
}